{
  "dayKey": "26.3.11",
  "date": "2026-03-11",
  "editorialGuidance": [
    "Keep the tone concise, professional, and specific.",
    "Lead with user-facing outcomes, shipping milestones, trust wins, and installability improvements.",
    "Demote internal cleanup unless it clearly changes the shipped product."
  ],
  "pinnedHighlights": [],
  "editorialNotes": [],
  "rollup": {
    "summary": "Add structured file logging and overnight-freeze timeout guards",
    "whatsNew": [
      "Add structured file logging and overnight-freeze timeout guards"
    ],
    "fixes": [
      "Clean CI test failures and automate PWA release deployment"
    ],
    "performance": []
  },
  "updatedAt": "2026-04-02T02:45:02.470Z"
}
